README.md
setup.cfg
setup.py
pythontron/__init__.py
pythontron/functions.py
pythontron.egg-info/PKG-INFO
pythontron.egg-info/SOURCES.txt
pythontron.egg-info/dependency_links.txt
pythontron.egg-info/not-zip-safe
pythontron.egg-info/requires.txt
pythontron.egg-info/top_level.txt