Metadata-Version: 1.0
Name: pythontron
Version: 1.1
Summary: Python library for creating perceptrons.
Home-page: http://github.com/HonestHacker123/pythontron
Author: Makar Kuznetsov
Author-email: makar10kuznetsov@mail.ru
License: UNKNOWN
Platform: UNKNOWN
